szpt_course/__init__.py
szpt_course/common.py
szpt_course/course.py
szpt_course/model.py
SZPT_Course-0.1.3.dist-info/METADATA
SZPT_Course-0.1.3.dist-info/WHEEL
SZPT_Course-0.1.3.dist-info/top_level.txt
SZPT_Course-0.1.3.dist-info/RECORD
