Metadata-Version: 2.1
Name: SZPT-Course
Version: 0.1.3
Summary: A simple Course query Python package for SZPT.
Home-page: https://github.com/HsOjo/SZPT-Course/
Author: HsOjo
Author-email: hsojo@qq.com
License: UNKNOWN
Keywords: hsojo python3 szpt course
Platform: UNKNOWN
Classifier: Programming Language :: Python :: 3
Classifier: License :: OSI Approved :: MIT License
Classifier: Operating System :: OS Independent
Requires-Python: >=3.6
Requires-Dist: requests
